{
  "ru": {
    "translation": {
      "go_to_profile": "Вернуться в мой профиль",
      "go_to_home": "Вернуться на главную страницу",
      "quantity": "Количество",
      "price": "Цена",
      "total_price": "Итоговая цена",
      "cart_empty": "В корзине ничего нет",
      "books_0": "{{count}} книга",
      "books_1": "{{count}} книги",
      "books_2": "{{count}} книг",
      "items_0": "{{count}} Предмета",
      "items_1": "{{count}} Предмета",
      "items_2": "{{count}} Предметов",
      "no_data": "Нету данных",
      "menu_main": "Главная",
      "menu_about": "О Нас",
      "menu_categories": "Категории",
      "menu_profile": "Мой профиль",
      "menu_logout": "Выйти",
      "menu_signin": "Войти",
      "menu_signup": "Зарегистрироватся",
      "home_page": "Домашняя страница",
      "popular_book": "Полпулярные книги",
      "loading": "Загрузка...",
      "lang": "Язык",
      "search_book": "Поиск книг",
      "search": "Поиск",
      "results": "Результатов",
      "details": "Подробнее...",
      "add_to_cart": "Добавить в корзину",
      "create_password": "Придумайте пароль",
      "password": "Пароль",
      "message_password": "Пожалуйста введите парооль",
      "message_email": "Пожалуйста введите ваш адрес электронной почты",
      "message_username": "Введите Ваше имя",
      "email": "Email",
      "username": "Ваше имя",
      "terms": "Я согласен с условиями использования услуги, а также с передачей и обработкой моих данных",
      "confirm_email_message": "Проверьте свою учетную запись электронной почты и подтвердите ее.",
      "confirm_success": "Ваша учетная запись была подтверждена.",
      "confirm_error": "Недопустимый токен",
      "contacts": "НАШИ КОНТАКТЫ",
      "socials": "МЫ В СОЦ-СЕТЯХ",
      "about": "О НАС",
      "bookstore_help": "О МАГАЗИНЕ",
      "bookstore_desc": "Книжный магазин Bookstore располагается на улице Arcadian Дриве, 3306 в центре Сан-франциско. Прогуливаясь по этажам этого книжного магазина, можно легко провести здесь полдня, проходя из отдела с литературой о музыке в секцию иностранной литературы. По мнению многих жителей Берлина, именно в Bookstore - наиболее широкий ассортимент книг различной тематики на английском языке"
    }
  }
}
